{
  "sections": [
    {
      "id": "sec-1",
      "title": "Общие сведения",
      "subsections": [
        {
          "id": "sec-1-1",
          "title": "Назначение",
          "blocks": [
            {
              "text": "Демонстрационный JSON описывает иерархию, как на схеме: верхний заголовок, подзаголовки, внутри — блоки текста и иллюстраций.",
              "imageUrl": "https://picsum.photos/seed/json-a/640/360"
            },
            {
              "text": "Тот же подраздел может содержать несколько блоков: например, отдельный абзац без картинки."
            }
          ]
        },
        {
          "id": "sec-1-2",
          "title": "Как пользоваться",
          "blocks": [
            {
              "text": "Выберите строку в списке разделов и нажмите «Открыть выбранный» или кнопку внизу списка.",
              "imageUrl": "https://picsum.photos/seed/json-b/640/360"
            }
          ]
        }
      ]
    },
    {
      "id": "sec-2",
      "title": "Техника безопасности при работе на ПК",
      "subsections": [
        {
          "id": "sec-2-1",
          "title": "Организация рабочего места",
          "blocks": [
            {
              "text": "Экран верхней кромкой на уровне глаз или чуть ниже; расстояние до монитора 50–70 см; естественное или комбинированное освещение без бликов.",
              "imageUrl": "https://picsum.photos/seed/json-c/640/360"
            }
          ]
        },
        {
          "id": "sec-2-2",
          "title": "Перерывы",
          "blocks": [
            {
              "text": "Каждые 45–60 минут интенсивной работы делайте паузу 5–10 минут: отвести взгляд вдаль, размять плечи и кисти."
            }
          ]
        }
      ]
    },
    {
      "id": "sec-3",
      "title": "Справочные материалы",
      "subsections": [
        {
          "id": "sec-3-1",
          "title": "Глоссарий",
          "blocks": [
            {
              "text": "JSON — текстовый формат обмена данными; HTTPS — защищённый протокол; Avalonia — кроссплатформенный UI-фреймворк для .NET.",
              "imageUrl": "https://picsum.photos/seed/json-d/640/360"
            }
          ]
        }
      ]
    }
  ]
}
